quantaxis_run/__init__.py
quantaxis_run/query.py
quantaxis_run/run_backend.py
quantaxis_run/setting.py
quantaxis_run-1.9.dist-info/METADATA
quantaxis_run-1.9.dist-info/WHEEL
quantaxis_run-1.9.dist-info/top_level.txt
quantaxis_run-1.9.dist-info/zip-safe
quantaxis_run-1.9.dist-info/RECORD
