Metadata-Version: 2.1
Name: quantaxis-run
Version: 1.9
Summary: QUANTAXIS:Quantitative Financial Strategy Framework
Home-page: https://github.com/yutiansut/quantaxis_run
Author: yutiansut
Author-email: yutiansut@qq.com
License: MIT
Keywords: quantaxis,quant,finance,Backtest,Framework
Platform: UNKNOWN
Classifier: License :: OSI Approved :: MIT License
Classifier: Programming Language :: Python
Classifier: Intended Audience :: Developers
Classifier: Operating System :: OS Independent
Requires-Dist: celery (>4)
Requires-Dist: quantaxis (>=1.3.1)
